eigolingo/__init__.py
eigolingo/__main__.py
eigolingo/wdicts/__init__.py
eigolingo/wdicts/contraction_dict.txt
eigolingo/wdicts/dict70.txt
eigolingo/wdicts/dict80.txt
eigolingo/wdicts/dict95.txt
eigolingo/wdicts/total_counter.txt
eigolingo-0.0.4.dist-info/entry_points.txt
eigolingo-0.0.4.dist-info/LICENSE
eigolingo-0.0.4.dist-info/WHEEL
eigolingo-0.0.4.dist-info/METADATA
eigolingo-0.0.4.dist-info/RECORD
