Metadata-Version: 2.1
Name: eigolingo
Version: 0.0.4
Summary: Determine the number of unique words in a given text/string
Keywords: english,linguistics,unique words
Author: exc4l
Author-email: cps0537@gmail.com
Requires-Python: >=3.8,<4.0
Classifier: Development Status :: 3 - Alpha
Classifier: Intended Audience :: Education
Classifier: Intended Audience :: End Users/Desktop
Classifier: Natural Language :: English
Classifier: Programming Language :: Python :: 3
Classifier: Programming Language :: Python :: 3.8
Classifier: Programming Language :: Python :: 3.9
Classifier: Topic :: Text Processing :: Linguistic
Requires-Dist: numpy (>=1.20.2,<2.0.0)
Requires-Dist: pandas (>=1.2.4,<2.0.0)
Requires-Dist: tqdm (>=4.60.0,<5.0.0)
